[
  {"id": "mr-1", "name": "Zack Snyder's Justice League (2021 film)", "value": 242, "image": "https://picsum.photos/seed/mr-0/320/240"},
  {"id": "mr-2", "name": "Gone with the Wind (1939 film)", "value": 238, "image": "https://picsum.photos/seed/mr-1/320/240"},
  {"id": "mr-3", "name": "The Ten Commandments (1956 film)", "value": 231, "image": "https://picsum.photos/seed/mr-2/320/240"},
  {"id": "mr-4", "name": "Lawrence of Arabia (1962 film)", "value": 227, "image": "https://picsum.photos/seed/mr-3/320/240"},
  {"id": "mr-5", "name": "Ben-Hur (1959 film)", "value": 214, "image": "https://picsum.photos/seed/mr-4/320/240"},
  {"id": "mr-6", "name": "The Irishman (2019 film)", "value": 209, "image": "https://picsum.photos/seed/mr-5/320/240"},
  {"id": "mr-7", "name": "Avengers: Infinity War (2018 film)", "value": 206, "image": "https://picsum.photos/seed/mr-6/320/240"},
  {"id": "mr-8", "name": "The Lord of the Rings: The Return of the King (2003 film)", "value": 201, "image": "https://picsum.photos/seed/mr-7/320/240"},
  {"id": "mr-9", "name": "Schindler's List (1993 film)", "value": 199, "image": "https://picsum.photos/seed/mr-8/320/240"},
  {"id": "mr-10", "name": "Titanic (1997 film)", "value": 195, "image": "https://picsum.photos/seed/mr-9/320/240"},
  {"id": "mr-11", "name": "Avatar: The Way of Water (2022 film)", "value": 192, "image": "https://picsum.photos/seed/mr-10/320/240"},
  {"id": "mr-12", "name": "The Green Mile (1999 film)", "value": 189, "image": "https://picsum.photos/seed/mr-11/320/240"},
  {"id": "mr-13", "name": "King Kong (2005 film)", "value": 187, "image": "https://picsum.photos/seed/mr-12/320/240"},
  {"id": "mr-14", "name": "The Wolf of Wall Street (2013 film)", "value": 184, "image": "https://picsum.photos/seed/mr-13/320/240"},
  {"id": "mr-15", "name": "Avengers: Endgame (2019 film)", "value": 182, "image": "https://picsum.photos/seed/mr-14/320/240"},
  {"id": "mr-16", "name": "Oppenheimer (2023 film)", "value": 181, "image": "https://picsum.photos/seed/mr-15/320/240"},
  {"id": "mr-17", "name": "The Batman (2022 film)", "value": 176, "image": "https://picsum.photos/seed/mr-16/320/240"},
  {"id": "mr-18", "name": "Interstellar (2014 film)", "value": 169, "image": "https://picsum.photos/seed/mr-17/320/240"},
  {"id": "mr-19", "name": "Dune: Part Two (2024 film)", "value": 166, "image": "https://picsum.photos/seed/mr-18/320/240"},
  {"id": "mr-20", "name": "No Time to Die (2021 film)", "value": 163, "image": "https://picsum.photos/seed/mr-19/320/240"},
  {"id": "mr-21", "name": "Once Upon a Time in Hollywood (2019 film)", "value": 161, "image": "https://picsum.photos/seed/mr-20/320/240"},
  {"id": "mr-22", "name": "Dune (2021 film)", "value": 155, "image": "https://picsum.photos/seed/mr-21/320/240"},
  {"id": "mr-23", "name": "The Dark Knight (2008 film)", "value": 152, "image": "https://picsum.photos/seed/mr-22/320/240"},
  {"id": "mr-24", "name": "Blade Runner 2049 (2017 film)", "value": 149, "image": "https://picsum.photos/seed/mr-23/320/240"},
  {"id": "mr-25", "name": "Gladiator (2000 film)", "value": 148, "image": "https://picsum.photos/seed/mr-24/320/240"},
  {"id": "mr-26", "name": "Inception (2010 film)", "value": 145, "image": "https://picsum.photos/seed/mr-25/320/240"},
  {"id": "mr-27", "name": "Mad Max: Fury Road (2015 film)", "value": 142, "image": "https://picsum.photos/seed/mr-26/320/240"},
  {"id": "mr-28", "name": "The Matrix (1999 film)", "value": 139, "image": "https://picsum.photos/seed/mr-27/320/240"},
  {"id": "mr-29", "name": "Spider-Man: Into the Spider-Verse (2018 film)", "value": 136, "image": "https://picsum.photos/seed/mr-28/320/240"},
  {"id": "mr-30", "name": "Top Gun: Maverick (2022 film)", "value": 131, "image": "https://picsum.photos/seed/mr-29/320/240"},
  {"id": "mr-31", "name": "The Grand Budapest Hotel (2014 film)", "value": 100, "image": "https://picsum.photos/seed/mr-30/320/240"},
  {"id": "mr-32", "name": "Toy Story (1995 film)", "value": 81, "image": "https://picsum.photos/seed/mr-31/320/240"}
]
